{"cameraMode":{"drawMode":0,"name":"Shaded","section":"Shading Mode"},"sceneLighting":false,"audioPlay":false,"sceneViewState":{"m_AlwaysRefresh":true,"showFog":false,"showSkybox":false,"showFlares":false,"showImageEffects":false,"showParticleSystems":true,"showVisualEffectGraphs":true,"m_FxEnabled":true},"in2DMode":false,"pivot":{"x":-16.46346664428711,"y":-4.934399604797363,"z":5.880234241485596},"rotation":{"x":0.4120183289051056,"y":0.3175155818462372,"z":-0.15642036497592927,"w":0.8398086428642273},"size":59.65838623046875,"orthographic":false}